forestadmin/agent_toolkit/__init__.py
forestadmin/agent_toolkit/agent.py
forestadmin/agent_toolkit/exceptions.py
forestadmin/agent_toolkit/forest_logger.py
forestadmin/agent_toolkit/options.py
forestadmin/agent_toolkit/resources/__init__.py
forestadmin/agent_toolkit/resources/actions/__init__.py
forestadmin/agent_toolkit/resources/actions/requests.py
forestadmin/agent_toolkit/resources/actions/resources.py
forestadmin/agent_toolkit/resources/base.py
forestadmin/agent_toolkit/resources/capabilities.py
forestadmin/agent_toolkit/resources/collections/__init__.py
forestadmin/agent_toolkit/resources/collections/base_collection_resource.py
forestadmin/agent_toolkit/resources/collections/charts_collection.py
forestadmin/agent_toolkit/resources/collections/charts_datasource.py
forestadmin/agent_toolkit/resources/collections/crud.py
forestadmin/agent_toolkit/resources/collections/crud_related.py
forestadmin/agent_toolkit/resources/collections/decorators.py
forestadmin/agent_toolkit/resources/collections/exceptions.py
forestadmin/agent_toolkit/resources/collections/filter.py
forestadmin/agent_toolkit/resources/collections/native_query.py
forestadmin/agent_toolkit/resources/collections/requests.py
forestadmin/agent_toolkit/resources/collections/stats.py
forestadmin/agent_toolkit/resources/context_variable_injector_mixin.py
forestadmin/agent_toolkit/resources/ip_white_list_resource.py
forestadmin/agent_toolkit/resources/security/__init__.py
forestadmin/agent_toolkit/resources/security/exceptions.py
forestadmin/agent_toolkit/resources/security/resources.py
forestadmin/agent_toolkit/services/__init__.py
forestadmin/agent_toolkit/services/permissions/__init__.py
forestadmin/agent_toolkit/services/permissions/ip_whitelist_service.py
forestadmin/agent_toolkit/services/permissions/options.py
forestadmin/agent_toolkit/services/permissions/permission_service.py
forestadmin/agent_toolkit/services/permissions/permissions_functions.py
forestadmin_agent_toolkit-1.23.9.dist-info/METADATA
forestadmin_agent_toolkit-1.23.9.dist-info/WHEEL
forestadmin_agent_toolkit-1.23.9.dist-info/RECORD
